CausalViz/__init__.py
causalviz-0.2.0.dist-info/LICENSE
causalviz-0.2.0.dist-info/METADATA
causalviz-0.2.0.dist-info/WHEEL
causalviz-0.2.0.dist-info/top_level.txt
causalviz-0.2.0.dist-info/RECORD
