Metadata-Version: 2.1
Name: causalviz
Version: 0.2.0
Summary: 一个用于低维数据的因果推断可视化的Python包，该包通过一层神经网络的拟合来还原X对Y的因果关系，并且对其进行可视化。同时，该包能够实现对调节效应的自动分析与可视化。
Author: xiezhenyuan-dashuaibi
Author-email: 546091915@qq.com
Requires-Python: >=3.6
License-File: LICENSE
Requires-Dist: numpy
Requires-Dist: pandas
Requires-Dist: scipy
Requires-Dist: seaborn
Requires-Dist: torch
Requires-Dist: matplotlib
